README
setup.py
pythonmarketo/__init__.py
pythonmarketo/client.py
pythonmarketo.egg-info/PKG-INFO
pythonmarketo.egg-info/SOURCES.txt
pythonmarketo.egg-info/dependency_links.txt
pythonmarketo.egg-info/requires.txt
pythonmarketo.egg-info/top_level.txt
pythonmarketo/helper/__init__.py
pythonmarketo/helper/exceptions.py
pythonmarketo/helper/http_lib.py