Metadata-Version: 1.0
Name: pythonmarketo
Version: 0.0.8
Summary: Wrapper to Marketo Rest API.
Home-page: https://github.com/asamat/python_marketo
Author: Arunim Samat
Author-email: arunimsamat@gmail.com
License: MIT License
Platform: UNKNOWN
